s3simplified-0.1.2.dist-info/licenses/LICENSE
src/__init__.py
src/main.py
s3simplified-0.1.2.dist-info/METADATA
s3simplified-0.1.2.dist-info/WHEEL
s3simplified-0.1.2.dist-info/top_level.txt
s3simplified-0.1.2.dist-info/RECORD
