Metadata-Version: 2.4
Name: s3simplified
Version: 0.1.2
Summary: Simple AWS S3 operations library
Author-email: Ian <iandanmathenge@gmail.com>
License: MIT
Project-URL: Homepage, https://github.com/IanDanielM/boto3-s3-simple-library
Classifier: Programming Language :: Python :: 3
Classifier: License :: OSI Approved :: MIT License
Classifier: Operating System :: OS Independent
Requires-Python: >=3.10
License-File: LICENSE
Requires-Dist: boto3>=1.38.12
Requires-Dist: build>=1.2.2.post1
Requires-Dist: twine>=6.1.0
Dynamic: license-file
